gendo/__init__.py
gendo/bot.py
gendo/exceptions.py
gendo/scheduler.py
gendo/utils.py
gendobot-4.1.4.dist-info/DESCRIPTION.rst
gendobot-4.1.4.dist-info/METADATA
gendobot-4.1.4.dist-info/RECORD
gendobot-4.1.4.dist-info/WHEEL
gendobot-4.1.4.dist-info/metadata.json
gendobot-4.1.4.dist-info/top_level.txt
