Metadata-Version: 2.0
Name: gendobot
Version: 4.1.4
Summary: a lightweight Slackbot framework for Python
Home-page: http://nickficano.com
Author: Nick Ficano
Author-email: nficano@gmail.com
License: Copyright (c) 2017 Nick Ficano
Requires-Dist: crontab (==0.21.3)
Requires-Dist: jinja2 (==2.9.6)
Requires-Dist: python-box (==3.0.1)
Requires-Dist: pyyaml (==3.12)
Requires-Dist: slackclient (==1.0.6)
